dbautomate/__init__.py
dbautomate/mongodboperator.py
dbautomate/mysqloperator.py
dbautomate-0.5.6.dist-info/METADATA
dbautomate-0.5.6.dist-info/WHEEL
dbautomate-0.5.6.dist-info/top_level.txt
dbautomate-0.5.6.dist-info/RECORD
