Metadata-Version: 2.1
Name: dbautomate
Version: 0.5.6
Summary: A Python package for connecting with database.
Home-page: https://github.com/ravi46931/dbautomatepkg
Author: ravi46931
Author-email: ravikumar46931@gmail.com
License: MIT
Project-URL: Bug Tracker, https://github.com/ravi46931/dbautomatepkg/issues
Classifier: Programming Language :: Python :: 3.7
Classifier: Programming Language :: Python :: 3.8
Classifier: Programming Language :: Python :: 3.9
Classifier: Programming Language :: Python :: 3.11
Classifier: Operating System :: OS Independent
Requires-Python: >=3.7
Requires-Dist: pymongo
Requires-Dist: pymongo[srv]
Requires-Dist: dnspython
Requires-Dist: pandas
Requires-Dist: numpy
Requires-Dist: ensure
Requires-Dist: pytest
Requires-Dist: termcolor
Requires-Dist: mysql-connector-python
Requires-Dist: prettytable
Provides-Extra: testing
Requires-Dist: pytest >=7.1.3 ; extra == 'testing'
Requires-Dist: mypy >=0.971 ; extra == 'testing'
Requires-Dist: flake8 >=5.0.4 ; extra == 'testing'
Requires-Dist: tox >=3.25.1 ; extra == 'testing'
Requires-Dist: black >=22.8.0 ; extra == 'testing'
